pyrometheus/__init__.py
pyrometheus/__main__.py
pyrometheus/chem_expr.py
pyrometheus/cli.py
pyrometheus/codegen/__init__.py
pyrometheus/codegen/cpp.py
pyrometheus/codegen/fortran.py
pyrometheus/codegen/python.py
pyrometheus-1.0.6.dist-info/METADATA
pyrometheus-1.0.6.dist-info/WHEEL
pyrometheus-1.0.6.dist-info/entry_points.txt
pyrometheus-1.0.6.dist-info/licenses/LICENSE
pyrometheus-1.0.6.dist-info/RECORD
